app/__init__.py
app/main.py
wkhtmltopdf_api-0.1.0.dist-info/METADATA
wkhtmltopdf_api-0.1.0.dist-info/WHEEL
wkhtmltopdf_api-0.1.0.dist-info/entry_points.txt
wkhtmltopdf_api-0.1.0.dist-info/top_level.txt
wkhtmltopdf_api-0.1.0.dist-info/RECORD
